RDGen/__init__.py
RDGen/generator.py
RDGen-1.0.1.dist-info/LICENSE
RDGen-1.0.1.dist-info/METADATA
RDGen-1.0.1.dist-info/WHEEL
RDGen-1.0.1.dist-info/top_level.txt
RDGen-1.0.1.dist-info/RECORD
