Metadata-Version: 2.1
Name: RDGen
Version: 1.0.1
Summary: A reusable 2D dungeon generator for Python projects
Author: Robert Tilton
Author-email: RobertJTilton89@gmail.com
License: MIT
Classifier: Programming Language :: Python :: 3
Classifier: License :: OSI Approved :: MIT License
Classifier: Operating System :: OS Independent
Requires-Python: >=3.6
License-File: LICENSE
Requires-Dist: colorama==0.4.6
